equation_painter_wsm/__init__.py
equation_painter_wsm/__main__.py
equation_painter_wsm-1.2.1.data/scripts/eqpaint
equation_painter_wsm-1.2.1.dist-info/LICENSE
equation_painter_wsm-1.2.1.dist-info/METADATA
equation_painter_wsm-1.2.1.dist-info/WHEEL
equation_painter_wsm-1.2.1.dist-info/entry_points.txt
equation_painter_wsm-1.2.1.dist-info/top_level.txt
equation_painter_wsm-1.2.1.dist-info/RECORD
