Metadata-Version: 2.1
Name: equation-painter-wsm
Version: 1.2.1
Summary: A way for teachers to make equation painter worksheets for their students.
Home-page: https://github.com/cole-wilson/wsm
Author: Cole Wilson
Author-email: cole@colewilson.xyz
License: MIT
Platform: UNKNOWN
Classifier: Programming Language :: Python :: 3
Requires-Python: >=3.6
Requires-Dist: requests
Requires-Dist: pillow
Requires-Dist: xlsxwriter
